moneymade_connect_python_sdk/__init__.py
moneymade_connect_python_sdk/moneymade_connect.py
moneymade_connect_python_sdk/test_moneymade_connect.py
moneymade_connect_oauth_python_sdk-0.0.11.dist-info/LICENSE
moneymade_connect_oauth_python_sdk-0.0.11.dist-info/METADATA
moneymade_connect_oauth_python_sdk-0.0.11.dist-info/WHEEL
moneymade_connect_oauth_python_sdk-0.0.11.dist-info/top_level.txt
moneymade_connect_oauth_python_sdk-0.0.11.dist-info/RECORD
