Metadata-Version: 2.1
Name: moneymade-connect-oauth-python-sdk
Version: 0.0.11
Summary: Packages which makes simplier integration with MoneyMade OAuth feature
Author-email: vitalik@moneymade.io
License: UNKNOWN
Project-URL: Documentation, https://pypi.org/project/moneymade-connect-oauth-python-sdk
Project-URL: Source, https://github.com/moneymadeio/moneymade-connect-python-sdk
Platform: UNKNOWN
Requires-Python: >=3.7, <4
License-File: LICENSE
Requires-Dist: requests (==2.26.0)
